bluedot/__init__.py
bluedot/app.py
bluedot/btcomm.py
bluedot/colors.py
bluedot/constants.py
bluedot/dot.py
bluedot/exceptions.py
bluedot/interactions.py
bluedot/mock.py
bluedot/threads.py
bluedot/utils.py
bluedot-2.0.0.dist-info/LICENSE
bluedot-2.0.0.dist-info/METADATA
bluedot-2.0.0.dist-info/WHEEL
bluedot-2.0.0.dist-info/entry_points.txt
bluedot-2.0.0.dist-info/top_level.txt
bluedot-2.0.0.dist-info/RECORD
