Metadata-Version: 2.1
Name: bluedot
Version: 2.0.0
Summary: A zero boiler plate bluetooth remote
Home-page: https://github.com/martinohanlon/BlueDot
Author: Martin O'Hanlon
Author-email: martin@ohanlonweb.com
License: MIT
Keywords: raspberry,pi,raspberry pi,bluetooth,remote,android
Platform: UNKNOWN
Classifier: Development Status :: 5 - Production/Stable
Classifier: Intended Audience :: Education
Classifier: Intended Audience :: Developers
Classifier: Topic :: Education
Classifier: Topic :: Communications
Classifier: License :: OSI Approved :: MIT License
Classifier: Programming Language :: Python :: 3
Classifier: Programming Language :: Python :: 3.5
Classifier: Programming Language :: Python :: 3.6
Classifier: Programming Language :: Python :: 3.7
Classifier: Programming Language :: Python :: 3.8
